Metadata-Version: 2.1
Name: authenticus
Version: 0.0.0
Summary: Authenticus (under development)
Home-page: https://github.com/azurystudio/authenticus
Author: Filippo Romani
Author-email: mail@filipporomani.it
Classifier: Programming Language :: Python :: 3
Classifier: Programming Language :: Python :: 3.8
Classifier: Programming Language :: Python :: 3.9
Classifier: Programming Language :: Python :: 3.10
Classifier: Programming Language :: Python :: 3.11
Classifier: Topic :: Software Development :: Libraries :: Python Modules
Classifier: License :: OSI Approved :: MIT License
Classifier: Operating System :: OS Independent
Requires-Python: >=3
